<annotation>
	<folder>snap</folder>
	<filename>Screenshot from 2023-12-19 10-57-10.png</filename>
	<path>/home/lenovo/snap/Screenshot from 2023-12-19 10-57-10.png</path>
	<source>
		<database>Unknown</database>
	</source>
	<size>
		<width>1231</width>
		<height>616</height>
		<depth>3</depth>
	</size>
	<segmented>0</segmented>
	<object>
		<name>menu-bar</name>
		<pose>Unspecified</pose>
		<truncated>0</truncated>
		<difficult>0</difficult>
		<bndbox>
			<xmin>6</xmin>
			<ymin>6</ymin>
			<xmax>1223</xmax>
			<ymax>57</ymax>
		</bndbox>
	</object>
</annotation>
